<?xml version="1.0" encoding="utf-8" ?>
<dwsync>
<file name="blank.gif" server="sftp.itd.umich.edu//afs/umich.edu/group/m/michitdv/Public/html/" local="129095291960000000" remote="129095291960000000" Dst="1" />
<file name="fancy_nav_right.png" server="sftp.itd.umich.edu//afs/umich.edu/group/m/michitdv/Public/html/" local="131523192980000000" remote="131523192980000000" Dst="1" />
<file name="fancy_loading.png" server="sftp.itd.umich.edu//afs/umich.edu/group/m/michitdv/Public/html/" local="129110047340000000" remote="129110047340000000" Dst="1" />
<file name="fancy_loading_blank.png" server="sftp.itd.umich.edu//afs/umich.edu/group/m/michitdv/Public/html/" local="129110047340000000" remote="129110047340000000" Dst="1" />
<file name="fancy_nav_left.png" server="sftp.itd.umich.edu//afs/umich.edu/group/m/michitdv/Public/html/" local="131523192850000000" remote="131523192850000000" Dst="1" />
<file name="fancy_close.png" server="sftp.itd.umich.edu//afs/umich.edu/group/m/michitdv/Public/html/" local="131523192140000000" remote="131523192140000000" Dst="1" />
<file name="fancy_title_left.png" server="sftp.itd.umich.edu//afs/umich.edu/group/m/michitdv/Public/html/" local="129096124340000000" remote="129096124340000000" Dst="1" />
<file name="fancy_title_main.png" server="sftp.itd.umich.edu//afs/umich.edu/group/m/michitdv/Public/html/" local="129096124340000000" remote="129096124340000000" Dst="1" />
<file name="fancy_title_right.png" server="sftp.itd.umich.edu//afs/umich.edu/group/m/michitdv/Public/html/" local="129096124340000000" remote="129096124340000000" Dst="1" />
<file name="jquery.easing-1.3.pack.js" server="sftp.itd.umich.edu//afs/umich.edu/group/m/michitdv/Public/html/" local="129115292850000000" remote="129115292850000000" Dst="1" />
<file name="jquery.fancybox-1.3.0.css" server="sftp.itd.umich.edu//afs/umich.edu/group/m/michitdv/Public/html/" local="131523204330000000" remote="131523204330000000" Dst="1" />
<file name="jquery.fancybox-1.3.0.js" server="sftp.itd.umich.edu//afs/umich.edu/group/m/michitdv/Public/html/" local="131199911790000000" remote="131199911790000000" Dst="1" />
<file name="jquery.fancybox-1.3.0.pack.js" server="sftp.itd.umich.edu//afs/umich.edu/group/m/michitdv/Public/html/" local="131199911920000000" remote="131199911920000000" Dst="1" />
<file name="jquery.mousewheel-3.0.2.pack.js" server="sftp.itd.umich.edu//afs/umich.edu/group/m/michitdv/Public/html/" local="129115293930000000" remote="129115293930000000" Dst="1" />
<file name="zoom_in.gif" server="sftp.itd.umich.edu//afs/umich.edu/group/m/michitdv/Public/html/" local="129109167520000000" remote="129109167520000000" Dst="1" />
</dwsync>